AUTHORS.rst
CONTRIBUTING.rst
HISTORY.rst
LICENSE
MANIFEST.in
README.rst
setup.cfg
setup.py
docs/Makefile
docs/authors.rst
docs/conf.py
docs/contributing.rst
docs/history.rst
docs/index.rst
docs/installation.rst
docs/make.bat
docs/readme.rst
docs/usage.rst
python_arptable/__init__.py
python_arptable.egg-info/PKG-INFO
python_arptable.egg-info/SOURCES.txt
python_arptable.egg-info/dependency_links.txt
python_arptable.egg-info/not-zip-safe
python_arptable.egg-info/top_level.txt
tests/__init__.py
tests/test_python_arptable.py