Metadata-Version: 1.1
Name: python-arptable
Version: 0.0.2
Summary: Python simple arp table reader
Home-page: https://github.com/XayOn/python_arptable
Author: David Francos
Author-email: me@davidfrancos.net
License: BSD
Keywords: python_arptable
Platform: UNKNOWN
Classifier: Development Status :: 2 - Pre-Alpha
Classifier: Intended Audience :: Developers
Classifier: License :: OSI Approved :: BSD License
Classifier: Natural Language :: English
Classifier: Programming Language :: Python :: 2
Classifier: Programming Language :: Python :: 2.6
Classifier: Programming Language :: Python :: 2.7
Classifier: Programming Language :: Python :: 3
Classifier: Programming Language :: Python :: 3.3
Classifier: Programming Language :: Python :: 3.4
